{
    "results": {
        "E1v8": {
            "winner": "Cleveland Cavaliers",
            "inGames": null
        },
        "E4v5": {
            "winner": "Indiana Pacers",
            "inGames": null
        },
        "E3v6": {
            "winner": "TBD",
            "inGames": null
        },
        "E2v7": {
            "winner": "Boston Celtics",
            "inGames": null
        },
        "W1v8": {
            "winner": "Oklahoma City Thunder",
            "inGames": null
        },
        "W4v5": {
            "winner": "TBD",
            "inGames": null
        },
        "W3v6": {
            "winner": "TBD",
            "inGames": null
        },
        "W2v7": {
            "winner": "TBD",
            "inGames": null
        },
        "ESF1": {
            "winner": "TBD",
            "inGames": null
        },
        "ESF2": {
            "winner": "TBD",
            "inGames": null
        },
        "WSF1": {
            "winner": "TBD",
            "inGames": null
        },
        "WSF2": {
            "winner": "TBD",
            "inGames": null
        },
        "ECF": {
            "winner": "TBD",
            "inGames": null
        },
        "WCF": {
            "winner": "TBD",
            "inGames": null
        },
        "Finals": {
            "winner": "TBD",
            "inGames": null
        }
    }
}